pygame_ecs/__init__.py
pygame_ecs/entity.py
pygame_ecs/exceptions.py
pygame_ecs/components/__init__.py
pygame_ecs/components/base_component.py
pygame_ecs/managers/__init__.py
pygame_ecs/managers/component_manager.py
pygame_ecs/managers/entity_manager.py
pygame_ecs/managers/system_manager.py
pygame_ecs/systems/__init__.py
pygame_ecs/systems/base_system.py
pygame_ecs-0.4.0.dist-info/METADATA
pygame_ecs-0.4.0.dist-info/WHEEL
pygame_ecs-0.4.0.dist-info/licenses/LICENSE
pygame_ecs-0.4.0.dist-info/RECORD
