Metadata-Version: 2.3
Name: pygame_ecs
Version: 0.4.0
Summary: Pure Python, simple to use Entity Component System(ECS) for pygame
Project-URL: Homepage, https://github.com/Notenlish/pygame_ecs
Project-URL: Bug Tracker, https://github.com/Notenlish/pygame_ecs/issues
Author-email: Notenlish <71970100+Notenlish@users.noreply.github.com>
License-Expression: MIT
License-File: LICENSE
Keywords: ECS,component,ecs,entity,entity component system,pygame,pygame-ce,pygame_ecs,system
Classifier: Development Status :: 5 - Production/Stable
Classifier: Intended Audience :: Developers
Classifier: License :: OSI Approved :: MIT License
Classifier: Programming Language :: Python :: 3
Classifier: Programming Language :: Python :: 3.4
Classifier: Programming Language :: Python :: 3.5
Classifier: Programming Language :: Python :: 3.6
Classifier: Programming Language :: Python :: 3.7
Classifier: Programming Language :: Python :: 3.8
Classifier: Programming Language :: Python :: 3.9
Classifier: Programming Language :: Python :: 3.10
Classifier: Programming Language :: Python :: 3.11
Classifier: Programming Language :: Python :: 3.12
Classifier: Topic :: Software Development :: Build Tools
Requires-Python: >=3.7
